fediverse_features/__init__.py
fediverse_features/__main__.py
fediverse_features/gitignore.py
fediverse_features/latest_package.py
fediverse_features/test_gitignore.py
fediverse_features/test_init.py
fediverse_features/test_main.py
fediverse_features-0.1.4.dist-info/METADATA
fediverse_features-0.1.4.dist-info/WHEEL
fediverse_features-0.1.4.dist-info/entry_points.txt
fediverse_features-0.1.4.dist-info/RECORD
