Metadata-Version: 2.4
Name: fediverse-features
Version: 0.1.4
Summary: Helper to download fediverse feature files
Project-URL: Repository, https://codeberg.org/helge/fediverse-features
Requires-Python: >=3.11
Requires-Dist: click>=8.1.7
Requires-Dist: requests>=2.32.5
Requires-Dist: semver>=3.0.4
